PersistentObjects/__init__.py
PersistentObjects/core.py
persistentobjects-0.1.6.dist-info/licenses/LICENSE
persistentobjects-0.1.6.dist-info/METADATA
persistentobjects-0.1.6.dist-info/WHEEL
persistentobjects-0.1.6.dist-info/top_level.txt
persistentobjects-0.1.6.dist-info/RECORD
