Metadata-Version: 2.4
Name: PersistentObjects
Version: 0.1.6
Summary: JSON-backed attribute-persistent object with namespace support
Author: Tornado300
License-Expression: MIT
Classifier: Programming Language :: Python :: 3
Classifier: Operating System :: OS Independent
Requires-Python: >=3.10
License-File: LICENSE
Dynamic: license-file
